mkdocs_carbon_theme/__init__.py
mkdocs_carbon_theme/base.html.j2
mkdocs_carbon_theme/breadcrumbs.html.j2
mkdocs_carbon_theme/main.html
mkdocs_carbon_theme/mkdocs_theme.yml
mkdocs_carbon_theme/nav-footer.html.j2
mkdocs_carbon_theme/nav.html.j2
mkdocs_carbon_theme/search.html
mkdocs_carbon_theme/theme-toggle.html.j2
mkdocs_carbon_theme/toc.html.j2
mkdocs_carbon_theme/css/theme.css
mkdocs_carbon_theme/fonts/ibmplexmono-light.ttf
mkdocs_carbon_theme/fonts/ibmplexsans-light.ttf
mkdocs_carbon_theme/js/theme.js
mkdocs_carbon-2.1.0.dist-info/METADATA
mkdocs_carbon-2.1.0.dist-info/WHEEL
mkdocs_carbon-2.1.0.dist-info/entry_points.txt
mkdocs_carbon-2.1.0.dist-info/RECORD
