Metadata-Version: 2.4
Name: mkdocs-carbon
Version: 2.1.0
Summary: Carbon theme for MkDocs
Project-URL: Source, https://github.com/durera/mkdocs-carbon
Author-email: David Parker <durera@gmail.com>
License-Expression: EPL-2.0
Classifier: Development Status :: 4 - Beta
Classifier: Environment :: Web Environment
Classifier: Framework :: MkDocs
Classifier: Intended Audience :: Information Technology
Classifier: License :: OSI Approved :: Eclipse Public License 2.0 (EPL-2.0)
Classifier: Operating System :: OS Independent
Classifier: Programming Language :: Python
Classifier: Programming Language :: Python :: 3.10
Classifier: Programming Language :: Python :: 3.11
Classifier: Programming Language :: Python :: 3.12
Classifier: Programming Language :: Python :: 3.13
Classifier: Programming Language :: Python :: 3.14
Classifier: Topic :: Documentation
Requires-Dist: mkdocs>=1.5
Provides-Extra: dev
Requires-Dist: build; extra == 'dev'
Requires-Dist: twine; extra == 'dev'
